mathstropy/TextDisplay.py
mathstropy/TextInput.py
mathstropy/__init__.py
mathstropy/image_processing.py
mathstropy/miscellaneous_functions.py
mathstropy/ml.py
mathstropy/words.py
mathstropy/pgzero/__init__.py
mathstropy/pgzero/pgzero.py
mathstropy-4.0.7.dist-info/LICENSE
mathstropy-4.0.7.dist-info/METADATA
mathstropy-4.0.7.dist-info/WHEEL
mathstropy-4.0.7.dist-info/top_level.txt
mathstropy-4.0.7.dist-info/RECORD
